{
    "version": 4,
    "FrameData": {
        "SI.ConfigPageClass": "dabs.resources.configuration.resourcePages.SIPage",
        "SI.LINE_FORMAT_VERSION": 1,
        "SI.PREMIUM": true,
        "SI.TIFF_FORMAT_VERSION": 4,
        "SI.VERSION_COMMIT": "3a9a520ca68efdadcd0a8d3d4f98fcded5f943b9",
        "SI.VERSION_MAJOR": 2020,
        "SI.VERSION_MINOR": 1,
        "SI.VERSION_UPDATE": 3,
        "SI.acqState": "grab",
        "SI.acqsPerLoop": 1,
        "SI.errorMsg": "",
        "SI.extTrigEnable": false,
        "SI.fieldCurvatureRxs": [
            3700,
            3300,
            3150
        ],
        "SI.fieldCurvatureRys": [
            3700,
            3300,
            3150
        ],
        "SI.fieldCurvatureTilt": 70,
        "SI.fieldCurvatureTip": -70,
        "SI.fieldCurvatureZs": [
            0,
            360,
            700
        ],
        "SI.hBeams.enablePowerBox": false,
        "SI.hBeams.errorMsg": "",
        "SI.hBeams.flybackBlanking": true,
        "SI.hBeams.hBeamRouters": [],
        "SI.hBeams.hBeams": [
            "Chameleon",
            "Fidelity",
            "Stim Laser"
        ],
        "SI.hBeams.hReserver": [],
        "SI.hBeams.hUsers": [],
        "SI.hBeams.interlaceDecimation": [
            1,
            1,
            1
        ],
        "SI.hBeams.interlaceOffset": [
            0,
            0,
            0
        ],
        "SI.hBeams.lengthConstants": [
            Infinity,
            Infinity,
            Infinity
        ],
        "SI.hBeams.name": "SI Beams",
        "SI.hBeams.powerBoxEndFrame": Infinity,
        "SI.hBeams.powerBoxStartFrame": 1,
        "SI.hBeams.powerBoxes.rect": [
            0.25,
            0.25,
            0.5,
            0.5
        ],
        "SI.hBeams.powerBoxes.powers": [
            NaN,
            NaN,
            NaN
        ],
        "SI.hBeams.powerBoxes.name": "",
        "SI.hBeams.powerBoxes.oddLines": true,
        "SI.hBeams.powerBoxes.evenLines": true,
        "SI.hBeams.powerFractionLimits": [
            1,
            1,
            1
        ],
        "SI.hBeams.powerFractions": [
            0.7,
            0,
            0
        ],
        "SI.hBeams.powers": [
            70,
            0,
            0
        ],
        "SI.hBeams.pzAdjust": [
            false,
            false,
            false
        ],
        "SI.hBeams.pzCustom": [
            [],
            [],
            []
        ],
        "SI.hBeams.reserved": false,
        "SI.hBeams.reserverInfo": "",
        "SI.hBeams.totalNumBeams": 3,
        "SI.hBeams.userInfo": "",
        "SI.hBeams.warnMsg": "",
        "SI.hCameraManager.errorMsg": "",
        "SI.hCameraManager.hReserver": [],
        "SI.hCameraManager.hUsers": [],
        "SI.hCameraManager.name": "SI CameraManager",
        "SI.hCameraManager.reserved": false,
        "SI.hCameraManager.reserverInfo": "",
        "SI.hCameraManager.userInfo": "",
        "SI.hCameraManager.warnMsg": "",
        "SI.hChannels.channelAdcResolution": [
            14,
            14
        ],
        "SI.hChannels.channelDisplay": 1,
        "SI.hChannels.channelInputRange": [
            [
                -1,
                1
            ],
            [
                -1,
                1
            ]
        ],
        "SI.hChannels.channelLUT": [
            [
                -23,
                683
            ],
            [
                0,
                100
            ]
        ],
        "SI.hChannels.channelMergeColor": [
            "red",
            "red",
            "red",
            "red"
        ],
        "SI.hChannels.channelName": [
            "Channel 1",
            "Channel 2"
        ],
        "SI.hChannels.channelOffset": [
            36,
            115
        ],
        "SI.hChannels.channelSave": 1,
        "SI.hChannels.channelSubtractOffset": [
            true,
            true
        ],
        "SI.hChannels.channelType": [
            "stripe",
            "stripe"
        ],
        "SI.hChannels.channelsActive": 1,
        "SI.hChannels.channelsAvailable": 2,
        "SI.hChannels.errorMsg": "",
        "SI.hChannels.hReserver": [],
        "SI.hChannels.hUsers": [],
        "SI.hChannels.loggingEnable": 1,
        "SI.hChannels.name": "SI Channels",
        "SI.hChannels.reserved": false,
        "SI.hChannels.reserverInfo": "",
        "SI.hChannels.userInfo": "",
        "SI.hChannels.warnMsg": "",
        "SI.hConfigurationSaver.cfgFilename": "F:\\config\\Dan_CompAdjust.cfg",
        "SI.hConfigurationSaver.errorMsg": "",
        "SI.hConfigurationSaver.hReserver": [],
        "SI.hConfigurationSaver.hUsers": [],
        "SI.hConfigurationSaver.name": "SI ConfigurationSaver",
        "SI.hConfigurationSaver.reserved": false,
        "SI.hConfigurationSaver.reserverInfo": "",
        "SI.hConfigurationSaver.userInfo": "",
        "SI.hConfigurationSaver.usrFilename": "F:\\config\\Dan_CompAdjust.usr",
        "SI.hConfigurationSaver.warnMsg": "",
        "SI.hCoordinateSystems.errorMsg": "",
        "SI.hCoordinateSystems.hReserver": [],
        "SI.hCoordinateSystems.hUsers": [],
        "SI.hCoordinateSystems.name": "SI CoordinateSystems",
        "SI.hCoordinateSystems.reserved": false,
        "SI.hCoordinateSystems.reserverInfo": "",
        "SI.hCoordinateSystems.userInfo": "",
        "SI.hCoordinateSystems.warnMsg": "",
        "SI.hCycleManager.cycleIterIdxTotal": 0,
        "SI.hCycleManager.cyclesCompleted": 0,
        "SI.hCycleManager.enabled": false,
        "SI.hCycleManager.errorMsg": "",
        "SI.hCycleManager.hReserver": [],
        "SI.hCycleManager.hUsers": [],
        "SI.hCycleManager.itersCompleted": 0,
        "SI.hCycleManager.name": "SI CycleManager",
        "SI.hCycleManager.reserved": false,
        "SI.hCycleManager.reserverInfo": "",
        "SI.hCycleManager.totalCycles": 1,
        "SI.hCycleManager.userInfo": "",
        "SI.hCycleManager.warnMsg": "",
        "SI.hDisplay.autoScaleSaturationFraction": [
            0.1,
            0.01
        ],
        "SI.hDisplay.channelsMergeEnable": false,
        "SI.hDisplay.channelsMergeFocusOnly": false,
        "SI.hDisplay.displayRollingAverageFactor": 1,
        "SI.hDisplay.displayRollingAverageFactorLock": false,
        "SI.hDisplay.enableScanfieldDisplays": false,
        "SI.hDisplay.errorMsg": "",
        "SI.hDisplay.hReserver": [],
        "SI.hDisplay.hUsers": [],
        "SI.hDisplay.lineScanHistoryLength": 1000,
        "SI.hDisplay.name": "SI Display",
        "SI.hDisplay.renderer": "auto",
        "SI.hDisplay.reserved": false,
        "SI.hDisplay.reserverInfo": "",
        "SI.hDisplay.scanfieldDisplayColumns": 5,
        "SI.hDisplay.scanfieldDisplayRows": 5,
        "SI.hDisplay.scanfieldDisplayTilingMode": "Auto",
        "SI.hDisplay.scanfieldDisplays.enable": false,
        "SI.hDisplay.scanfieldDisplays.name": "Display 1",
        "SI.hDisplay.scanfieldDisplays.channel": 1,
        "SI.hDisplay.scanfieldDisplays.roi": 1,
        "SI.hDisplay.scanfieldDisplays.z": 0,
        "SI.hDisplay.selectedZs": [],
        "SI.hDisplay.showScanfieldDisplayNames": true,
        "SI.hDisplay.userInfo": "",
        "SI.hDisplay.volumeDisplayStyle": "3D",
        "SI.hDisplay.warnMsg": "",
        "SI.hFastZ.actuatorLag": 0.0015,
        "SI.hFastZ.discardFlybackFrames": false,
        "SI.hFastZ.enable": true,
        "SI.hFastZ.enableFieldCurveCorr": 1,
        "SI.hFastZ.errorMsg": "",
        "SI.hFastZ.flybackTime": 0.005,
        "SI.hFastZ.hReserver": [],
        "SI.hFastZ.hUsers": [],
        "SI.hFastZ.hasFastZ": true,
        "SI.hFastZ.name": "SI FastZ",
        "SI.hFastZ.numDiscardFlybackFrames": 0,
        "SI.hFastZ.position": 1300,
        "SI.hFastZ.reserved": false,
        "SI.hFastZ.reserverInfo": "",
        "SI.hFastZ.userInfo": "",
        "SI.hFastZ.volumePeriodAdjustment": -0.0006,
        "SI.hFastZ.warnMsg": "",
        "SI.hFastZ.waveformType": "step",
        "SI.hIntegrationRoiManager.enable": false,
        "SI.hIntegrationRoiManager.enableDisplay": true,
        "SI.hIntegrationRoiManager.errorMsg": "",
        "SI.hIntegrationRoiManager.hReserver": [],
        "SI.hIntegrationRoiManager.hUsers": [],
        "SI.hIntegrationRoiManager.integrationHistoryLength": 1000,
        "SI.hIntegrationRoiManager.name": "SI IntegrationRoiManager",
        "SI.hIntegrationRoiManager.outputChannelsEnabled": [],
        "SI.hIntegrationRoiManager.outputChannelsFunctions": [],
        "SI.hIntegrationRoiManager.outputChannelsNames": [],
        "SI.hIntegrationRoiManager.outputChannelsPhysicalNames": [],
        "SI.hIntegrationRoiManager.outputChannelsRoiNames": [],
        "SI.hIntegrationRoiManager.postProcessFcn": "@scanimage.components.integrationRois.integrationPostProcessingFcn",
        "SI.hIntegrationRoiManager.reserved": false,
        "SI.hIntegrationRoiManager.reserverInfo": "",
        "SI.hIntegrationRoiManager.userInfo": "",
        "SI.hIntegrationRoiManager.warnMsg": "",
        "SI.hMotionManager.correctionBoundsXY": [
            -5,
            5
        ],
        "SI.hMotionManager.correctionBoundsZ": [
            -100,
            100
        ],
        "SI.hMotionManager.correctionDeviceXY": "galvos",
        "SI.hMotionManager.correctionDeviceZ": "fastz",
        "SI.hMotionManager.correctionEnableXY": true,
        "SI.hMotionManager.correctionEnableZ": true,
        "SI.hMotionManager.correctorClassName": "scanimage.components.motionCorrectors.MariusMotionCorrector2",
        "SI.hMotionManager.enable": true,
        "SI.hMotionManager.errorMsg": "",
        "SI.hMotionManager.estimatorClassName": "scanimage.components.motionEstimators.MariusMotionEstimator",
        "SI.hMotionManager.hReserver": [],
        "SI.hMotionManager.hUsers": [],
        "SI.hMotionManager.motionHistoryLength": 100,
        "SI.hMotionManager.motionMarkersXY": [],
        "SI.hMotionManager.name": "SI MotionManager",
        "SI.hMotionManager.reserved": false,
        "SI.hMotionManager.reserverInfo": "",
        "SI.hMotionManager.resetCorrectionAfterAcq": 0,
        "SI.hMotionManager.userInfo": "",
        "SI.hMotionManager.warnMsg": "",
        "SI.hMotionManager.zStackAlignmentFcn": "@scanimage.components.motionEstimators.util.alignZRoiData",
        "SI.hMotors.ConfigPageClass": "dabs.resources.configuration.resourcePages.SIMotorsPage",
        "SI.hMotors.axesPosition": [
            0,
            0,
            0
        ],
        "SI.hMotors.azimuth": 0,
        "SI.hMotors.elevation": 0,
        "SI.hMotors.errorMsg": "",
        "SI.hMotors.errorTf": false,
        "SI.hMotors.hReserver": [],
        "SI.hMotors.hUsers": [],
        "SI.hMotors.isAligned": false,
        "SI.hMotors.isHomed": true,
        "SI.hMotors.isRelativeZeroSet": false,
        "SI.hMotors.maxZStep": Infinity,
        "SI.hMotors.minPositionQueryInterval_s": 0.001,
        "SI.hMotors.motorErrorMsg": "",
        "SI.hMotors.moveInProgress": false,
        "SI.hMotors.moveTimeout_s": 10,
        "SI.hMotors.name": "SI Motors",
        "SI.hMotors.reserved": false,
        "SI.hMotors.reserverInfo": "",
        "SI.hMotors.samplePosition": [
            0,
            0,
            0
        ],
        "SI.hMotors.simulatedAxes": [
            true,
            true,
            true
        ],
        "SI.hMotors.userDefinedPositions": [],
        "SI.hMotors.userInfo": "",
        "SI.hMotors.warnMsg": "",
        "SI.hPhotostim.ConfigPageClass": "dabs.resources.configuration.resourcePages.SIPhotostimPage",
        "SI.hPhotostim.allowMultipleOutputs": false,
        "SI.hPhotostim.autoTriggerPeriod": 0,
        "SI.hPhotostim.compensateMotionEnabled": true,
        "SI.hPhotostim.completedSequences": 0,
        "SI.hPhotostim.errorMsg": "",
        "SI.hPhotostim.hReserver": [],
        "SI.hPhotostim.hUsers": [],
        "SI.hPhotostim.laserActiveSignalAdvance": 0.001,
        "SI.hPhotostim.lastMotion": [
            0,
            0
        ],
        "SI.hPhotostim.logging": false,
        "SI.hPhotostim.monitoring": false,
        "SI.hPhotostim.monitoringSampleRate": 9000,
        "SI.hPhotostim.name": "SI Photostim",
        "SI.hPhotostim.nextStimulus": 1,
        "SI.hPhotostim.numOutputs": 0,
        "SI.hPhotostim.numSequences": Infinity,
        "SI.hPhotostim.reserved": false,
        "SI.hPhotostim.reserverInfo": "",
        "SI.hPhotostim.sequencePosition": 1,
        "SI.hPhotostim.sequenceSelectedStimuli": [],
        "SI.hPhotostim.status": "Offline",
        "SI.hPhotostim.stimImmediately": false,
        "SI.hPhotostim.stimSelectionAssignment": [],
        "SI.hPhotostim.stimSelectionDevice": "",
        "SI.hPhotostim.stimSelectionTerms": [],
        "SI.hPhotostim.stimSelectionTriggerTerm": [],
        "SI.hPhotostim.stimTriggerTerm": 1,
        "SI.hPhotostim.stimulusMode": "onDemand",
        "SI.hPhotostim.syncTriggerTerm": [],
        "SI.hPhotostim.userInfo": "",
        "SI.hPhotostim.warnMsg": "",
        "SI.hPhotostim.zMode": "2D",
        "SI.hPmts.autoPower": false,
        "SI.hPmts.bandwidths": 0,
        "SI.hPmts.errorMsg": "",
        "SI.hPmts.gains": 0,
        "SI.hPmts.hReserver": [],
        "SI.hPmts.hUsers": [],
        "SI.hPmts.name": "SI Pmts",
        "SI.hPmts.names": "Both",
        "SI.hPmts.offsets": 0,
        "SI.hPmts.powersOn": false,
        "SI.hPmts.reserved": false,
        "SI.hPmts.reserverInfo": "",
        "SI.hPmts.tripped": false,
        "SI.hPmts.userInfo": "",
        "SI.hPmts.warnMsg": "",
        "SI.hReserver": [],
        "SI.hRoiManager.errorMsg": "",
        "SI.hRoiManager.forceSquarePixelation": true,
        "SI.hRoiManager.forceSquarePixels": true,
        "SI.hRoiManager.hReserver": [],
        "SI.hRoiManager.hUsers": [],
        "SI.hRoiManager.imagingFovDeg": [],
        "SI.hRoiManager.imagingFovUm": [],
        "SI.hRoiManager.linePeriod": 4.16084e-05,
        "SI.hRoiManager.linesPerFrame": 512,
        "SI.hRoiManager.mroiEnable": 1,
        "SI.hRoiManager.name": "SI RoiManager",
        "SI.hRoiManager.pixelsPerLine": 512,
        "SI.hRoiManager.reserved": false,
        "SI.hRoiManager.reserverInfo": "",
        "SI.hRoiManager.scanAngleMultiplierFast": 1,
        "SI.hRoiManager.scanAngleMultiplierSlow": 1,
        "SI.hRoiManager.scanAngleShiftFast": 0,
        "SI.hRoiManager.scanAngleShiftSlow": 0,
        "SI.hRoiManager.scanFramePeriod": 0.0949504,
        "SI.hRoiManager.scanFrameRate": 10.5318,
        "SI.hRoiManager.scanRotation": 0,
        "SI.hRoiManager.scanType": "frame",
        "SI.hRoiManager.scanVolumeRate": 10.5318,
        "SI.hRoiManager.scanZoomFactor": 15,
        "SI.hRoiManager.userInfo": "",
        "SI.hRoiManager.warnMsg": "",
        "SI.hScan2D.ConfigPageClass": "dabs.resources.configuration.resourcePages.ResScanPage",
        "SI.hScan2D.auxTriggersEnable": true,
        "SI.hScan2D.beamClockDelay": 1.5e-06,
        "SI.hScan2D.beamClockExtend": 0,
        "SI.hScan2D.bidirectional": true,
        "SI.hScan2D.channelOffsets": [
            36,
            115
        ],
        "SI.hScan2D.channels": [],
        "SI.hScan2D.channelsAdcResolution": 14,
        "SI.hScan2D.channelsAutoReadOffsets": true,
        "SI.hScan2D.channelsAvailable": 2,
        "SI.hScan2D.channelsDataType": "int16",
        "SI.hScan2D.channelsFilter": "Bessel",
        "SI.hScan2D.channelsInputRanges": [
            [
                -1,
                1
            ],
            [
                -1,
                1
            ]
        ],
        "SI.hScan2D.channelsInvert": [
            false,
            false
        ],
        "SI.hScan2D.channelsSubtractOffsets": [
            true,
            true
        ],
        "SI.hScan2D.errorMsg": "",
        "SI.hScan2D.externalSampleClock": false,
        "SI.hScan2D.externalSampleClockRate": 80000000.0,
        "SI.hScan2D.fillFractionSpatial": 0.9,
        "SI.hScan2D.fillFractionTemporal": 0.712867,
        "SI.hScan2D.flybackTimePerFrame": 0.005,
        "SI.hScan2D.flytoTimePerScanfield": 0.005,
        "SI.hScan2D.fovCornerPoints": [
            [
                -18.2695,
                -20
            ],
            [
                18.2695,
                -20
            ],
            [
                18.2695,
                20
            ],
            [
                -18.2695,
                20
            ]
        ],
        "SI.hScan2D.hReserver": [],
        "SI.hScan2D.hUsers": [],
        "SI.hScan2D.hasResonantMirror": true,
        "SI.hScan2D.hasXGalvo": true,
        "SI.hScan2D.keepResonantScannerOn": false,
        "SI.hScan2D.laserTriggerDebounceTicks": 0,
        "SI.hScan2D.laserTriggerPort": "",
        "SI.hScan2D.laserTriggerSampleMaskEnable": false,
        "SI.hScan2D.laserTriggerSampleWindow": [
            0,
            1
        ],
        "SI.hScan2D.linePhase": -2.975e-06,
        "SI.hScan2D.linePhaseMode": "Nearest Neighbor",
        "SI.hScan2D.logAverageFactor": 1,
        "SI.hScan2D.logFramesPerFile": 500,
        "SI.hScan2D.logFramesPerFileLock": false,
        "SI.hScan2D.logOverwriteWarn": 1,
        "SI.hScan2D.mask": [
            [
                9
            ],
            [
                9
            ],
            [
                9
            ],
            [
                9
            ],
            [
                9
            ],
            [
                9
            ],
            [
                8
            ],
            [
                8
            ],
            [
                9
            ],
            [
                8
            ],
            [
                8
            ],
            [
                8
            ],
            [
                8
            ],
            [
                8
            ],
            [
                7
            ],
            [
                8
            ],
            [
                7
            ],
            [
                8
            ],
            [
                7
            ],
            [
                7
            ],
            [
                8
            ],
            [
                7
            ],
            [
                7
            ],
            [
                7
            ],
            [
                7
            ],
            [
                7
            ],
            [
                7
            ],
            [
                6
            ],
            [
                7
            ],
            [
                7
            ],
            [
                6
            ],
            [
                7
            ],
            [
                6
            ],
            [
                7
            ],
            [
                6
            ],
            [
                7
            ],
            [
                6
            ],
            [
                6
            ],
            [
                7
            ],
            [
                6
            ],
            [
                6
            ],
            [
                6
            ],
            [
                6
            ],
            [
                6
            ],
            [
                6
            ],
            [
                6
            ],
            [
                6
            ],
            [
                6
            ],
            [
                6
            ],
            [
                6
            ],
            [
                5
            ],
            [
                6
            ],
            [
                6
            ],
            [
                6
            ],
            [
                5
            ],
            [
                6
            ],
            [
                6
            ],
            [
                5
            ],
            [
                6
            ],
            [
                5
            ],
            [
                6
            ],
            [
                5
            ],
            [
                6
            ],
            [
                5
            ],
            [
                6
            ],
            [
                5
            ],
            [
                6
            ],
            [
                5
            ],
            [
                5
            ],
            [
                6
            ],
            [
                5
            ],
            [
                5
            ],
            [
                5
            ],
            [
                6
            ],
            [
                5
            ],
            [
                5
            ],
            [
                5
            ],
            [
                5
            ],
            [
                5
            ],
            [
                6
            ],
            [
                5
            ],
            [
                5
            ],
            [
                5
            ],
            [
                5
            ],
            [
                5
            ],
            [
                5
            ],
            [
                5
            ],
            [
                5
            ],
            [
                5
            ],
            [
                5
            ],
            [
                5
            ],
            [
                5
            ],
            [
                5
            ],
            [
                4
            ],
            [
                5
            ],
            [
                5
            ],
            [
                5
            ],
            [
                5
            ],
            [
                5
            ],
            [
                4
            ],
            [
                5
            ],
            [
                5
            ],
            [
                5
            ],
            [
                5
            ],
            [
                4
            ],
            [
                5
            ],
            [
                5
            ],
            [
                4
            ],
            [
                5
            ],
            [
                5
            ],
            [
                5
            ],
            [
                4
            ],
            [
                5
            ],
            [
                4
            ],
            [
                5
            ],
            [
                5
            ],
            [
                4
            ],
            [
                5
            ],
            [
                5
            ],
            [
                4
            ],
            [
                5
            ],
            [
                4
            ],
            [
                5
            ],
            [
                4
            ],
            [
                5
            ],
            [
                4
            ],
            [
                5
            ],
            [
                4
            ],
            [
                5
            ],
            [
                4
            ],
            [
                5
            ],
            [
                4
            ],
            [
                5
            ],
            [
                4
            ],
            [
                5
            ],
            [
                4
            ],
            [
                5
            ],
            [
                4
            ],
            [
                5
            ],
            [
                4
            ],
            [
                4
            ],
            [
                5
            ],
            [
                4
            ],
            [
                5
            ],
            [
                4
            ],
            [
                4
            ],
            [
                5
            ],
            [
                4
            ],
            [
                4
            ],
            [
                5
            ],
            [
                4
            ],
            [
                4
            ],
            [
                5
            ],
            [
                4
            ],
            [
                4
            ],
            [
                5
            ],
            [
                4
            ],
            [
                4
            ],
            [
                5
            ],
            [
                4
            ],
            [
                4
            ],
            [
                5
            ],
            [
                4
            ],
            [
                4
            ],
            [
                4
            ],
            [
                5
            ],
            [
                4
            ],
            [
                4
            ],
            [
                5
            ],
            [
                4
            ],
            [
                4
            ],
            [
                4
            ],
            [
                4
            ],
            [
                5
            ],
            [
                4
            ],
            [
                4
            ],
            [
                4
            ],
            [
                5
            ],
            [
                4
            ],
            [
                4
            ],
            [
                4
            ],
            [
                4
            ],
            [
                5
            ],
            [
                4
            ],
            [
                4
            ],
            [
                4
            ],
            [
                4
            ],
            [
                5
            ],
            [
                4
            ],
            [
                4
            ],
            [
                4
            ],
            [
                4
            ],
            [
                5
            ],
            [
                4
            ],
            [
                4
            ],
            [
                4
            ],
            [
                4
            ],
            [
                4
            ],
            [
                5
            ],
            [
                4
            ],
            [
                4
            ],
            [
                4
            ],
            [
                4
            ],
            [
                4
            ],
            [
                4
            ],
            [
                5
            ],
            [
                4
            ],
            [
                4
            ],
            [
                4
            ],
            [
                4
            ],
            [
                4
            ],
            [
                4
            ],
            [
                5
            ],
            [
                4
            ],
            [
                4
            ],
            [
                4
            ],
            [
                4
            ],
            [
                4
            ],
            [
                4
            ],
            [
                5
            ],
            [
                4
            ],
            [
                4
            ],
            [
                4
            ],
            [
                4
            ],
            [
                4
            ],
            [
                4
            ],
            [
                4
            ],
            [
                5
            ],
            [
                4
            ],
            [
                4
            ],
            [
                4
            ],
            [
                4
            ],
            [
                4
            ],
            [
                4
            ],
            [
                5
            ],
            [
                4
            ],
            [
                4
            ],
            [
                4
            ],
            [
                4
            ],
            [
                4
            ],
            [
                4
            ],
            [
                4
            ],
            [
                5
            ],
            [
                4
            ],
            [
                4
            ],
            [
                4
            ],
            [
                4
            ],
            [
                4
            ],
            [
                4
            ],
            [
                5
            ],
            [
                4
            ],
            [
                4
            ],
            [
                4
            ],
            [
                4
            ],
            [
                4
            ],
            [
                4
            ],
            [
                5
            ],
            [
                4
            ],
            [
                4
            ],
            [
                4
            ],
            [
                4
            ],
            [
                4
            ],
            [
                4
            ],
            [
                5
            ],
            [
                4
            ],
            [
                4
            ],
            [
                4
            ],
            [
                4
            ],
            [
                4
            ],
            [
                5
            ],
            [
                4
            ],
            [
                4
            ],
            [
                4
            ],
            [
                4
            ],
            [
                5
            ],
            [
                4
            ],
            [
                4
            ],
            [
                4
            ],
            [
                4
            ],
            [
                5
            ],
            [
                4
            ],
            [
                4
            ],
            [
                4
            ],
            [
                4
            ],
            [
                5
            ],
            [
                4
            ],
            [
                4
            ],
            [
                4
            ],
            [
                5
            ],
            [
                4
            ],
            [
                4
            ],
            [
                4
            ],
            [
                4
            ],
            [
                5
            ],
            [
                4
            ],
            [
                4
            ],
            [
                5
            ],
            [
                4
            ],
            [
                4
            ],
            [
                4
            ],
            [
                5
            ],
            [
                4
            ],
            [
                4
            ],
            [
                5
            ],
            [
                4
            ],
            [
                4
            ],
            [
                5
            ],
            [
                4
            ],
            [
                4
            ],
            [
                5
            ],
            [
                4
            ],
            [
                4
            ],
            [
                5
            ],
            [
                4
            ],
            [
                4
            ],
            [
                5
            ],
            [
                4
            ],
            [
                4
            ],
            [
                5
            ],
            [
                4
            ],
            [
                5
            ],
            [
                4
            ],
            [
                4
            ],
            [
                5
            ],
            [
                4
            ],
            [
                5
            ],
            [
                4
            ],
            [
                5
            ],
            [
                4
            ],
            [
                5
            ],
            [
                4
            ],
            [
                5
            ],
            [
                4
            ],
            [
                5
            ],
            [
                4
            ],
            [
                5
            ],
            [
                4
            ],
            [
                5
            ],
            [
                4
            ],
            [
                5
            ],
            [
                4
            ],
            [
                5
            ],
            [
                4
            ],
            [
                5
            ],
            [
                5
            ],
            [
                4
            ],
            [
                5
            ],
            [
                5
            ],
            [
                4
            ],
            [
                5
            ],
            [
                4
            ],
            [
                5
            ],
            [
                5
            ],
            [
                5
            ],
            [
                4
            ],
            [
                5
            ],
            [
                5
            ],
            [
                4
            ],
            [
                5
            ],
            [
                5
            ],
            [
                5
            ],
            [
                5
            ],
            [
                4
            ],
            [
                5
            ],
            [
                5
            ],
            [
                5
            ],
            [
                5
            ],
            [
                5
            ],
            [
                4
            ],
            [
                5
            ],
            [
                5
            ],
            [
                5
            ],
            [
                5
            ],
            [
                5
            ],
            [
                5
            ],
            [
                5
            ],
            [
                5
            ],
            [
                5
            ],
            [
                5
            ],
            [
                5
            ],
            [
                5
            ],
            [
                5
            ],
            [
                6
            ],
            [
                5
            ],
            [
                5
            ],
            [
                5
            ],
            [
                5
            ],
            [
                5
            ],
            [
                6
            ],
            [
                5
            ],
            [
                5
            ],
            [
                5
            ],
            [
                6
            ],
            [
                5
            ],
            [
                5
            ],
            [
                6
            ],
            [
                5
            ],
            [
                6
            ],
            [
                5
            ],
            [
                6
            ],
            [
                5
            ],
            [
                6
            ],
            [
                5
            ],
            [
                6
            ],
            [
                5
            ],
            [
                6
            ],
            [
                6
            ],
            [
                5
            ],
            [
                6
            ],
            [
                6
            ],
            [
                6
            ],
            [
                5
            ],
            [
                6
            ],
            [
                6
            ],
            [
                6
            ],
            [
                6
            ],
            [
                6
            ],
            [
                6
            ],
            [
                6
            ],
            [
                6
            ],
            [
                6
            ],
            [
                6
            ],
            [
                6
            ],
            [
                7
            ],
            [
                6
            ],
            [
                6
            ],
            [
                7
            ],
            [
                6
            ],
            [
                7
            ],
            [
                6
            ],
            [
                7
            ],
            [
                6
            ],
            [
                7
            ],
            [
                7
            ],
            [
                6
            ],
            [
                7
            ],
            [
                7
            ],
            [
                7
            ],
            [
                7
            ],
            [
                7
            ],
            [
                7
            ],
            [
                8
            ],
            [
                7
            ],
            [
                7
            ],
            [
                8
            ],
            [
                7
            ],
            [
                8
            ],
            [
                7
            ],
            [
                8
            ],
            [
                8
            ],
            [
                8
            ],
            [
                8
            ],
            [
                8
            ],
            [
                9
            ],
            [
                8
            ],
            [
                8
            ],
            [
                9
            ],
            [
                9
            ],
            [
                9
            ],
            [
                9
            ],
            [
                9
            ],
            [
                9
            ]
        ],
        "SI.hScan2D.maskDisableAveraging": [
            false,
            false
        ],
        "SI.hScan2D.maxSampleRate": 80000000.0,
        "SI.hScan2D.name": "ResScanner",
        "SI.hScan2D.nominalFovCornerPoints": [
            [
                -18.2695,
                -20
            ],
            [
                18.2695,
                -20
            ],
            [
                18.2695,
                20
            ],
            [
                -18.2695,
                20
            ]
        ],
        "SI.hScan2D.parkSlmForAcquisition": true,
        "SI.hScan2D.physicalChannelsAvailable": 2,
        "SI.hScan2D.pixelBinFactor": 1,
        "SI.hScan2D.reserved": false,
        "SI.hScan2D.reserverInfo": "",
        "SI.hScan2D.sampleRate": 80000000.0,
        "SI.hScan2D.scanMode": "resonant",
        "SI.hScan2D.scanPixelTimeMaxMinRatio": 2.25,
        "SI.hScan2D.scanPixelTimeMean": 6.41775e-08,
        "SI.hScan2D.scannerFrequency": 12016.8,
        "SI.hScan2D.scannerToRefTransform": [
            [
                1,
                0,
                0
            ],
            [
                0,
                1,
                0
            ],
            [
                0,
                0,
                1
            ]
        ],
        "SI.hScan2D.scannerType": "RGG",
        "SI.hScan2D.settleTimeFraction": 0,
        "SI.hScan2D.simulated": false,
        "SI.hScan2D.stripingEnable": false,
        "SI.hScan2D.trigAcqEdge": "rising",
        "SI.hScan2D.trigAcqInTerm": "",
        "SI.hScan2D.trigNextEdge": "rising",
        "SI.hScan2D.trigNextInTerm": "",
        "SI.hScan2D.trigNextStopEnable": true,
        "SI.hScan2D.trigStopEdge": "rising",
        "SI.hScan2D.trigStopInTerm": "",
        "SI.hScan2D.uniformSampling": false,
        "SI.hScan2D.userInfo": "",
        "SI.hScan2D.warnMsg": "",
        "SI.hShutters.errorMsg": "",
        "SI.hShutters.hReserver": [],
        "SI.hShutters.hUsers": [],
        "SI.hShutters.name": "SI Shutters",
        "SI.hShutters.reserved": false,
        "SI.hShutters.reserverInfo": "",
        "SI.hShutters.userInfo": "",
        "SI.hShutters.warnMsg": "",
        "SI.hStackManager.actualNumSlices": 1,
        "SI.hStackManager.actualNumVolumes": 1000000.0,
        "SI.hStackManager.actualStackZStepSize": [],
        "SI.hStackManager.arbitraryZs": 1300,
        "SI.hStackManager.boundedStackDefinition": "numSlices",
        "SI.hStackManager.centeredStack": 1,
        "SI.hStackManager.closeShutterBetweenSlices": false,
        "SI.hStackManager.enable": true,
        "SI.hStackManager.errorMsg": "",
        "SI.hStackManager.framesPerSlice": 1,
        "SI.hStackManager.hReserver": [],
        "SI.hStackManager.hUsers": [],
        "SI.hStackManager.name": "SI StackManager",
        "SI.hStackManager.numFastZActuators": 1,
        "SI.hStackManager.numFramesPerVolume": 1,
        "SI.hStackManager.numFramesPerVolumeWithFlyback": 1,
        "SI.hStackManager.numSlices": 101,
        "SI.hStackManager.numVolumes": 1000000.0,
        "SI.hStackManager.reserved": false,
        "SI.hStackManager.reserverInfo": "",
        "SI.hStackManager.stackActuator": "fastZ",
        "SI.hStackManager.stackDefinition": "arbitrary",
        "SI.hStackManager.stackEndPower": [],
        "SI.hStackManager.stackFastWaveformType": "step",
        "SI.hStackManager.stackMode": "fast",
        "SI.hStackManager.stackReturnHome": true,
        "SI.hStackManager.stackStartPower": [],
        "SI.hStackManager.stackZEndPos": [],
        "SI.hStackManager.stackZStartPos": [],
        "SI.hStackManager.stackZStepSize": 0.5,
        "SI.hStackManager.useStartEndPowers": true,
        "SI.hStackManager.userInfo": "",
        "SI.hStackManager.warnMsg": "",
        "SI.hStackManager.zPowerReference": 1300,
        "SI.hStackManager.zs": 1300,
        "SI.hStackManager.zsAllActuators": 1300,
        "SI.hStackManager.zsRelative": 1300,
        "SI.hUserFunctions.errorMsg": "",
        "SI.hUserFunctions.hReserver": [],
        "SI.hUserFunctions.hUsers": [],
        "SI.hUserFunctions.name": "SI UserFunctions",
        "SI.hUserFunctions.reserved": false,
        "SI.hUserFunctions.reserverInfo": "",
        "SI.hUserFunctions.userFunctionsCfg__1.EventName": "acqModeStart",
        "SI.hUserFunctions.userFunctionsCfg__1.UserFcnName": "userFunctionBar",
        "SI.hUserFunctions.userFunctionsCfg__1.Arguments": [
            0
        ],
        "SI.hUserFunctions.userFunctionsCfg__1.Enable": false,
        "SI.hUserFunctions.userFunctionsCfg__2.EventName": "frameAcquired",
        "SI.hUserFunctions.userFunctionsCfg__2.UserFcnName": "userFunctionBar",
        "SI.hUserFunctions.userFunctionsCfg__2.Arguments": [
            0
        ],
        "SI.hUserFunctions.userFunctionsCfg__2.Enable": false,
        "SI.hUserFunctions.userFunctionsCfg__3.EventName": "frameAcquired",
        "SI.hUserFunctions.userFunctionsCfg__3.UserFcnName": "userFunctionBar",
        "SI.hUserFunctions.userFunctionsCfg__3.Arguments": [
            1
        ],
        "SI.hUserFunctions.userFunctionsCfg__3.Enable": false,
        "SI.hUserFunctions.userFunctionsUsr": [],
        "SI.hUserFunctions.userInfo": "",
        "SI.hUserFunctions.warnMsg": "",
        "SI.hUsers": [],
        "SI.hWSConnector.communicationTimeout": 5,
        "SI.hWSConnector.enable": false,
        "SI.hWSConnector.errorMsg": "",
        "SI.hWSConnector.hReserver": [],
        "SI.hWSConnector.hUsers": [],
        "SI.hWSConnector.name": "SI WSConnector",
        "SI.hWSConnector.reserved": false,
        "SI.hWSConnector.reserverInfo": "",
        "SI.hWSConnector.userInfo": "",
        "SI.hWSConnector.warnMsg": "",
        "SI.hWaveformManager.errorMsg": "",
        "SI.hWaveformManager.hReserver": [],
        "SI.hWaveformManager.hUsers": [],
        "SI.hWaveformManager.name": "SI WaveformManager",
        "SI.hWaveformManager.optimizedScanners": [],
        "SI.hWaveformManager.reserved": false,
        "SI.hWaveformManager.reserverInfo": "",
        "SI.hWaveformManager.userInfo": "",
        "SI.hWaveformManager.warnMsg": "",
        "SI.imagingSystem": "ResScanner",
        "SI.loopAcqInterval": 10,
        "SI.name": "ScanImage",
        "SI.objectiveResolution": 157.5,
        "SI.reserved": false,
        "SI.reserverInfo": "",
        "SI.shutDownScript": "",
        "SI.startUpScript": "resetMQTTServer",
        "SI.userInfo": "",
        "SI.warnMsg": ""
    },
    "RoiGroups": {
        "imagingRoiGroup": {
            "ver": 1,
            "classname": "scanimage.mroi.RoiGroup",
            "name": "DanCompAdj",
            "UserData": null,
            "roiUuid": "51B7CAB6C23BCD9A",
            "roiUuiduint64": 5.888397924e+18,
            "rois": [
                {
                    "ver": 1,
                    "classname": "scanimage.mroi.Roi",
                    "name": "",
                    "UserData": null,
                    "roiUuid": "886DD0C709B671AD",
                    "roiUuiduint64": 9.830743115e+18,
                    "zs": 1300,
                    "scanfields": {
                        "ver": 1,
                        "classname": "scanimage.mroi.scanfield.fields.RotatedRectangle",
                        "name": "",
                        "UserData": null,
                        "roiUuid": "5EA45D23E93C1FAC",
                        "roiUuiduint64": 6.819678145e+18,
                        "centerXY": [
                            -3.450500556,
                            -3.670745273
                        ],
                        "sizeXY": [
                            3.9051,
                            6.068965517
                        ],
                        "rotationDegrees": 0,
                        "enable": 1,
                        "pixelResolutionXY": [
                            462,
                            424
                        ],
                        "pixelToRefTransform": [
                            [
                                0.008452597403,
                                0,
                                -5.407276855
                            ],
                            [
                                0,
                                0.01431359792,
                                -6.71238483
                            ],
                            [
                                0,
                                0,
                                1
                            ]
                        ],
                        "affine": [
                            [
                                3.9051,
                                0,
                                -5.403050556
                            ],
                            [
                                0,
                                6.068965517,
                                -6.705228031
                            ],
                            [
                                0,
                                0,
                                1
                            ]
                        ]
                    },
                    "discretePlaneMode": 0,
                    "powers": null,
                    "pzAdjust": null,
                    "Lzs": null,
                    "interlaceDecimation": null,
                    "interlaceOffset": null,
                    "enable": 1
                },
                {
                    "ver": 1,
                    "classname": "scanimage.mroi.Roi",
                    "name": "",
                    "UserData": null,
                    "roiUuid": "EAD874F7DF70665A",
                    "roiUuiduint64": 1.692240421e+19,
                    "zs": 1300,
                    "scanfields": {
                        "ver": 1,
                        "classname": "scanimage.mroi.scanfield.fields.RotatedRectangle",
                        "name": "",
                        "UserData": null,
                        "roiUuid": "263140EE29C5DC5B",
                        "roiUuiduint64": 2.752052239e+18,
                        "centerXY": [
                            0.4545994438,
                            -2.789766407
                        ],
                        "sizeXY": [
                            3.9051,
                            10.3759733
                        ],
                        "rotationDegrees": 0,
                        "enable": 1,
                        "pixelResolutionXY": [
                            462,
                            818
                        ],
                        "pixelToRefTransform": [
                            [
                                0.008452597403,
                                0,
                                -1.502176855
                            ],
                            [
                                0,
                                0.01268456394,
                                -7.984095341
                            ],
                            [
                                0,
                                0,
                                1
                            ]
                        ],
                        "affine": [
                            [
                                3.9051,
                                0,
                                -1.497950556
                            ],
                            [
                                0,
                                10.3759733,
                                -7.977753059
                            ],
                            [
                                0,
                                0,
                                1
                            ]
                        ]
                    },
                    "discretePlaneMode": 0,
                    "powers": null,
                    "pzAdjust": null,
                    "Lzs": null,
                    "interlaceDecimation": null,
                    "interlaceOffset": null,
                    "enable": 1
                },
                {
                    "ver": 1,
                    "classname": "scanimage.mroi.Roi",
                    "name": "",
                    "UserData": null,
                    "roiUuid": "C29850F2ACDCB3B7",
                    "roiUuiduint64": 1.402204644e+19,
                    "zs": 1300,
                    "scanfields": {
                        "ver": 1,
                        "classname": "scanimage.mroi.scanfield.fields.RotatedRectangle",
                        "name": "",
                        "UserData": null,
                        "roiUuid": "8CFBD1E0B3796768",
                        "roiUuiduint64": 1.015894415e+19,
                        "centerXY": [
                            4.359699444,
                            -1.859844271
                        ],
                        "sizeXY": [
                            3.9051,
                            8.516129032
                        ],
                        "rotationDegrees": 0,
                        "enable": 1,
                        "pixelResolutionXY": [
                            462,
                            674
                        ],
                        "pixelToRefTransform": [
                            [
                                0.008452597403,
                                0,
                                2.402923145
                            ],
                            [
                                0,
                                0.01263520628,
                                -6.124226391
                            ],
                            [
                                0,
                                0,
                                1
                            ]
                        ],
                        "affine": [
                            [
                                3.9051,
                                0,
                                2.407149444
                            ],
                            [
                                0,
                                8.516129032,
                                -6.117908788
                            ],
                            [
                                0,
                                0,
                                1
                            ]
                        ]
                    },
                    "discretePlaneMode": 0,
                    "powers": null,
                    "pzAdjust": null,
                    "Lzs": null,
                    "interlaceDecimation": null,
                    "interlaceOffset": null,
                    "enable": 1
                }
            ]
        },
        "photostimRoiGroups": null,
        "integrationRoiGroup": {
            "ver": 1,
            "classname": "scanimage.mroi.RoiGroup",
            "name": "",
            "UserData": null,
            "roiUuid": "809B6483A831B924",
            "roiUuiduint64": 9.267111175e+18,
            "rois": {
                "_ArrayType_": "double",
                "_ArraySize_": [
                    1,
                    0
                ],
                "_ArrayData_": null
            }
        }
    }
}